exception_logger/__init__.py
exception_logger/json_logger.py
json_exception_logger-3.0.0.dist-info/METADATA
json_exception_logger-3.0.0.dist-info/WHEEL
json_exception_logger-3.0.0.dist-info/top_level.txt
json_exception_logger-3.0.0.dist-info/RECORD
