Metadata-Version: 2.1
Name: json_exception_logger
Version: 3.0.0
Author: Aayush Chaudhary
Requires-Python: >=3.6
Requires-Dist: python-dotenv
